privacygate/__init__.py
privacygate/auth.py
privacygate/client.py
privacygate/compat.py
privacygate/error.py
privacygate/response.py
privacygate/util.py
privacygate/version.py
privacygate/webhook.py
privacygate/api_resources/__init__.py
privacygate/api_resources/charge.py
privacygate/api_resources/checkout.py
privacygate/api_resources/event.py
privacygate/api_resources/base/__init__.py
privacygate/api_resources/base/api_object.py
privacygate/api_resources/base/api_resource.py
privacygate/api_resources/base/create_api_resource.py
privacygate/api_resources/base/delete_api_resource.py
privacygate/api_resources/base/list_api_resource.py
privacygate/api_resources/base/update_api_resource.py
privacygate-1.0.2.dist-info/LICENSE
privacygate-1.0.2.dist-info/METADATA
privacygate-1.0.2.dist-info/WHEEL
privacygate-1.0.2.dist-info/top_level.txt
privacygate-1.0.2.dist-info/RECORD
