Metadata-Version: 2.1
Name: privacygate
Version: 1.0.2
Summary: PrivacyGate API client library
Home-page: https://github.com/coinbase/coinbase-commerce-python
Author: Coinbase, Inc.
License: Apache 2.0
Keywords: api,coinbase commerce,client
Platform: UNKNOWN
Classifier: Intended Audience :: Developers
Classifier: License :: OSI Approved :: MIT License
Classifier: Operating System :: OS Independent
Classifier: Programming Language :: Python :: 2
Classifier: Programming Language :: Python :: 2.7
Classifier: Programming Language :: Python :: 3
Classifier: Programming Language :: Python :: 3.4
Classifier: Programming Language :: Python :: 3.5
Classifier: Programming Language :: Python :: 3.6
Classifier: Programming Language :: Python :: 3.7
Classifier: Programming Language :: Python
Classifier: Intended Audience :: Developers
Classifier: Topic :: Software Development :: Libraries :: Python Modules
License-File: LICENSE
Requires-Dist: requests (<3,>=2.14.0)
Requires-Dist: six (<2,>=1.9)
Provides-Extra: dev
Requires-Dist: nose (<2,>=1.3.4) ; extra == 'dev'
Requires-Dist: flake8 (<4,>=3.5.0) ; extra == 'dev'
Requires-Dist: coverage (<5,>=4) ; extra == 'dev'
Requires-Dist: unittest2 (<1,>=0.8.0) ; extra == 'dev'
Requires-Dist: mock (<3,>=2.0.0) ; extra == 'dev'
